{"app":"mozaic.link","date":"2023-01-05T13:45:50.419Z","name":"/FREE HTML Templates","type":"folder","children":[{"title":"HTML Templates Free Download by HTMLrev","type":"bookmark","url":"https://htmlrev.com/","icon":"https://htmlrev.com/images/html-templates.jpg"},{"title":"Free HTML Landing Page Templates and UI Kits | UIdeck","type":"bookmark","url":"https://uideck.com/","icon":"https://uideck.com/wp-content/uploads/2021/06/cropped-ud-symbol-180x180.jpg"},{"title":"https://html5up.net/","type":"bookmark","url":"https://html5up.net/","icon":"/static/images/noicon.png"},{"title":"576+ Free HTML CSS Website Templates by TemplateMo","type":"bookmark","url":"https://templatemo.com/","icon":"https://templatemo.com/banners/templatemo_600x400_2.jpg"},{"title":"Templates and Themes » W3Layouts","type":"bookmark","url":"https://w3layouts.com/templates/","icon":"https://w3layouts.com/favicon.ico"}],"color":"#74c0fc"}